README.md
setup.cfg
setup.py
zoomwrap/__init__.py
zoomwrap.egg-info/PKG-INFO
zoomwrap.egg-info/SOURCES.txt
zoomwrap.egg-info/dependency_links.txt
zoomwrap.egg-info/requires.txt
zoomwrap.egg-info/top_level.txt