Metadata-Version: 2.1
Name: zoomwrap
Version: 0.1.1
Summary: A module containing classes that can be easily serialized to JSON for use with Zoom's APIs.
Home-page: https://github.com/builderpepc/zoomwrap
Author: builderpepc
Author-email: troy.hiruka@gmail.com
License: MIT
Download-URL: https://github.com/builderpepc/zoomwrap/archive/v0.1.tar.gz
Keywords: zoom,zoom.us,zoom-api,bot
Platform: UNKNOWN
Classifier: Development Status :: 3 - Alpha
Classifier: Intended Audience :: Developers
Classifier: Topic :: Software Development :: Build Tools
Classifier: License :: OSI Approved :: MIT License
Classifier: Programming Language :: Python :: 3
Classifier: Programming Language :: Python :: 3.4
Classifier: Programming Language :: Python :: 3.5
Classifier: Programming Language :: Python :: 3.6
Classifier: Programming Language :: Python :: 3.7
Classifier: Programming Language :: Python :: 3.8
Classifier: Programming Language :: Python :: 3.9
